tad_dftd4/__init__.py
tad_dftd4/__version__.py
tad_dftd4/cutoff.py
tad_dftd4/defaults.py
tad_dftd4/disp.py
tad_dftd4/py.typed
tad_dftd4/utils.py
tad_dftd4/damping/__init__.py
tad_dftd4/damping/functions.py
tad_dftd4/damping/parameters/__init__.py
tad_dftd4/damping/parameters/base.py
tad_dftd4/damping/parameters/d3.toml
tad_dftd4/damping/parameters/d4.toml
tad_dftd4/damping/parameters/loader.py
tad_dftd4/data/__init__.py
tad_dftd4/data/hardness.py
tad_dftd4/data/r4r2.py
tad_dftd4/data/radii.py
tad_dftd4/data/wfpair.py
tad_dftd4/data/zeff.py
tad_dftd4/dispersion/__init__.py
tad_dftd4/dispersion/base.py
tad_dftd4/dispersion/d3.py
tad_dftd4/dispersion/d4.py
tad_dftd4/dispersion/threebody.py
tad_dftd4/dispersion/twobody.py
tad_dftd4/model/__init__.py
tad_dftd4/model/base.py
tad_dftd4/model/d3.py
tad_dftd4/model/d4.py
tad_dftd4/model/d4s.py
tad_dftd4/model/d5.py
tad_dftd4/model/typing.py
tad_dftd4/reference/__init__.py
tad_dftd4/reference/d4/__init__.py
tad_dftd4/reference/d4/charge_eeq.py
tad_dftd4/reference/d4/charge_gfn2.py
tad_dftd4/reference/d4/params.py
tad_dftd4-0.7.0.dist-info/licenses/LICENSE
tad_dftd4-0.7.0.dist-info/METADATA
tad_dftd4-0.7.0.dist-info/WHEEL
tad_dftd4-0.7.0.dist-info/top_level.txt
tad_dftd4-0.7.0.dist-info/RECORD
